Workbook

Sheet Overview
A1: HARSHDEEP GROUP — 90-Day Scale Engine
A2: Aurra Hype · Designomics India · Loop In Events | Powered in-house by Arihant Digital | Prepared Jul 2026
A4: THE THESIS
A5: One founder, four assets, one flywheel | B5: You already own a ~10-yr digital agency (Arihant Digital). Treat it as the in-house engine that builds & markets the three new brands at cost — then sell that same capability to outside clients as proof accumulates.
A6: Aurra Hype | B6: D2C streetwear / hype apparel (Bengaluru). Physical store + office launched 12 Jul. Sells online via aurahyped.com. Growth = product drops + performance ads + marketplace + quick-commerce.
A7: Designomics India | B7: Personalised gifting + merch + apparel (custom boxes, stickers, mugs, oversized tees, workshops, corporate gifting). Growth = corporate gifting contracts + custom-box e-comm + B2B2C.
A8: Loop In Events | B8: Event management & experiential. NAME CONFLICT: 'Loop In Events' + loopinevents.com already belong to an established Canadian planner (Michelle Munro). Rebrand + trademark strongly advised — see Roadmap & Doc.
A9: Arihant Digital (existing) | B9: The unfair advantage. Supplies web, performance marketing, SEO/GEO, automation & analytics to all three at internal cost, then externalises as a productised agency offer.
A11: HOW TO READ THIS WORKBOOK
A12: Master Stack | B12: Every service, software & automation the group needs, tagged by business, priority, in-house-vs-buy, vendor and cost.
A13: AI Automations | B13: Specific automations to build (trigger → action → tools → impact).
A14: 90-Day Roadmap | B14: Week-by-week plan across all three brands with the 'proof' KPI for each phase.
A15: Budget Summary | B15: Setup + monthly spend rolled up by domain (aggressive-spend scenario).
A16: Q-Commerce & Marketplaces | B16: Channel-by-channel onboarding tracker with real 2026 India costs & fit.
A18: LEGEND
A19: Priority | B19: P0 = do in Month 1 (foundation) · P1 = Month 2 (engine) · P2 = Month 3 (scale)
A20: In-house vs Buy | B20: In-house: Arihant = digital/marketing · In-house: Designomics = design/print/merch · Buy = external SaaS/vendor · Hybrid = both
A21: Costs | B21: INR. 'Aggressive spend to scale' scenario. Ad budgets are separate line items, not tool costs.

Sheet Master Stack
A1: MASTER STACK — Services · Software · Automations (all 3 brands)
A2: Aggressive-spend scenario · Ad budgets shown as monthly line items · In-house = built by Arihant/Designomics at internal cost
A4: # | B4: Business | C4: Domain | D4: Item / Capability | E4: What it does & why it matters | F4: Type | G4: Priority | H4: In-house vs Buy | I4: Recommended Tool / Vendor | J4: Setup (₹) | K4: Monthly (₹) | L4: Phase
A5: 1 | B5: Group | C5: Brand & Identity | D5: Group holding brand + naming architecture | E5: Define parent brand + how 3 sub-brands relate; fixes messy, inconsistent identity | F5: Service | G5: P0 | H5: In-house: Designomics | I5: Designomics design team | J5: 40000 | K5: 0 | L5: M1
A6: 2 | B6: Loop In | C6: Brand & Identity | D6: Rebrand (new name + logo + identity) | E6: Resolve Canada name clash; secure a distinct, trademarkable name | F6: Service | G6: P0 | H6: In-house: Designomics | I6: Designomics + IP attorney | J6: 60000 | K6: 0 | L6: M1
A7: 3 | B7: Aurra Hype | C7: Brand & Identity | D7: Brand guideline + logo refinement | E7: Distinguish from many 'Aura/Aurra' apparel brands; consistent look | F7: Service | G7: P0 | H7: In-house: Designomics | I7: Designomics design team | J7: 30000 | K7: 0 | L7: M1
A8: 4 | B8: Designomics | C8: Brand & Identity | D8: Brand system for gifting vs apparel lines | E8: Separate but linked identity for gifting box vs streetwear tees | F8: Service | G8: P1 | H8: In-house: Designomics | I8: Designomics design team | J8: 20000 | K8: 0 | L8: M2
A9: 5 | B9: Group | C9: Brand & Identity | D9: Trademark search + filing (per brand, key classes) | E9: Legal ownership of names/logos; blocks copycats | F9: Service | G9: P0 | H9: Buy | I9: IP attorney / Vakilsearch / IPIndia | J9: 45000 | K9: 0 | L9: M1
A10: 6 | B10: Aurra Hype | C10: Website & E-commerce | D10: Shopify store (migrate/upgrade) | E10: Fast, conversion-optimised storefront + apps ecosystem | F10: SaaS | G10: P0 | H10: In-house: Arihant | I10: Shopify (Basic→Growth) | J10: 25000 | K10: 3500 | L10: M1
A11: 7 | B11: Designomics | C11: Website & E-commerce | D11: Store upgrade / replatform from Wix | E11: Wix limits apps, speed, custom-box UX; move to Shopify | F11: SaaS | G11: P1 | H11: In-house: Arihant | I11: Shopify + custom-box app | J11: 30000 | K11: 3500 | L11: M2
A12: 8 | B12: Loop In | C12: Website & E-commerce | D12: Website + lead-capture + portfolio | E12: Booking enquiries, case studies, packages | F12: Service | G12: P0 | H12: In-house: Arihant | I12: Webflow / WordPress | J12: 25000 | K12: 1500 | L12: M1
A13: 9 | B13: Group | C13: Website & E-commerce | D13: Custom domains, SSL, email, DNS | E13: Professional infra across brands | F13: Infra | G13: P0 | H13: In-house: Arihant | I13: Google Workspace + Cloudflare | J13: 5000 | K13: 3000 | L13: M1
A14: 10 | B14: Aurra Hype | C14: Website & E-commerce | D14: Conversion apps (reviews, upsell, wishlist) | E14: Higher AOV & trust: Judge.me, ReConvert, Loox | F14: SaaS | G14: P1 | H14: Buy | I14: Judge.me / Loox / ReConvert | J14: 0 | K14: 4000 | L14: M2
A15: 11 | B15: Aurra Hype | C15: Website & E-commerce | D15: Site speed + CRO audit | E15: Cut bounce, lift conversion on paid traffic | F15: Service | G15: P1 | H15: In-house: Arihant | I15: Arihant CRO | J15: 15000 | K15: 0 | L15: M2
A16: 12 | B16: Group | C16: Content & Creative | D16: Product & lifestyle photography | E16: Sales-grade catalog + ad creative; current visuals weak | F16: Service | G16: P0 | H16: Hybrid | I16: In-house shoot + freelance photographer | J16: 60000 | K16: 20000 | L16: M1
... A83: 79 | B83: Group | C83: Analytics & BI | D83: Group KPI dashboard | E83: One board: revenue, CAC, AOV, ROAS per brand | F83: Service | G83: P1 | H83: In-house: Arihant | I83: Looker Studio + Arihant | J83: 0 | K83: 2000 | L83: M2
I84: TOTALS → | J84: =SUM(J5:J83) -> 835000 | K84: =SUM(K5:K83) -> 1120000

Sheet AI Automations
A1: AI & AUTOMATION CATALOGUE
A2: Build on n8n/Make + WhatsApp API + GPT/Claude. Each = trigger → action → impact.
A4: # | B4: Automation | C4: Business | D4: Trigger | E4: What it does | F4: Tools | G4: Impact
A5: 1 | B5: Abandoned-cart WhatsApp+email recovery | C5: Aurra Hype / Designomics | D5: Checkout started, not completed | E5: Sends timed WhatsApp + email with product image & discount | F5: Shopify + Klaviyo + AiSensy + n8n | G5: Recovers 8-15% lost carts
A6: 2 | B6: Order status auto-updates on WhatsApp | C6: All | D6: Order placed / shipped / OFD / delivered | E6: Auto WhatsApp with tracking at each stage | F6: Shiprocket + WhatsApp API + n8n | G6: Cuts 'where is my order' tickets ~60%
A7: 3 | B7: AI support chatbot (site + WhatsApp) | C7: All | D7: Customer message | E7: Answers sizing, returns, order status; hands off to human | F7: Chatbase/Intercom Fin + order API | G7: 24x7 support, faster conversion
A8: 4 | B8: Review + UGC request flow | C8: Aurra Hype / Designomics | D8: Order delivered +5 days | E8: Requests review + photo; rewards with coupon | F8: Judge.me/Loox + WhatsApp + n8n | G8: More social proof, repeat buyers
A9: 5 | B9: Daily ops digest to founder | C9: Group | D9: Every morning 8am | E9: Sales, ad spend, ROAS, top SKUs, low stock → WhatsApp | F9: Sheets + GA4 + Meta API + GPT + n8n | G9: One-glance control of 3 brands
A10: 6 | B10: Low-stock + reorder alerts | C10: All | D10: Stock < threshold | E10: Alerts + drafts PO to supplier | F10: Zoho Inventory + n8n + WhatsApp | G10: Prevents stockouts on winners
A11: 7 | B11: Lead capture → CRM → auto-reply | C11: Loop In / Designomics B2B | D11: Form / DM / ad lead | E11: Logs to CRM, sends intro + booking link, notifies sales | F11: Forms + Zoho CRM + n8n | G11: No lead dropped; faster follow-up
A12: 8 | B12: AI creative & caption generator | C12: Group | D12: New product / drop | E12: Generates ad copy, captions, descriptions, hashtags | F12: GPT/Claude + Canva API | G12: Cuts content time ~70%
A13: 9 | B13: AI product photo / on-model images | C13: Aurra Hype / Designomics | D13: New SKU added | E13: Generates lifestyle/on-model shots from flat-lay | F13: Photoroom/Flair + Midjourney | G13: Catalog-ready visuals, less shoot cost
A14: 10 | B14: RTO / COD risk flagging | C14: All | D14: COD order placed | E14: Scores risk; auto-verify high-risk via WhatsApp | F14: GoKwik / Shiprocket + n8n | G14: Reduces RTO losses
A15: 11 | B15: Influencer / UGC outreach at scale | C15: Aurra Hype | D15: Weekly | E15: Finds + DMs relevant micro-creators, tracks replies | F15: Sheets + IG + GPT + n8n | G15: Scales seeding cheaply
A16: 12 | B16: Auto marketplace listing sync | C16: Aurra Hype | D16: New/edited product | E16: Pushes SKU to Amazon/Flipkart with A+ copy | F16: Unicommerce + GPT + n8n | G16: List everywhere in minutes
... A19: 15 | B19: Birthday / occasion gifting reminders | C19: Designomics | D19: Date in CRM approaches | E19: Nudges customers to gift; pre-filled cart | F19: CRM + Klaviyo + WhatsApp | G19: Recurring gifting revenue

Sheet 90-Day Roadmap
A1: 90-DAY SCALE ROADMAP
A2: Month 1 Foundation · Month 2 Engine · Month 3 Scale. 'Proof' = the milestone that shows it's working.
A4: Phase | B4: Business | C4: Workstream | D4: Key Actions | E4: Owner | F4: Proof / KPI by end of phase
A5: M1 · Foundation (Wk 1-4) | B5: Group | C5: Legal + Brand | D5: Register/clean entities & GST; trademark search+file all 3; rebrand Loop In; unify brand systems | E5: Founder + CA + Designomics | F5: 3 TMs filed · Loop In new name live · brand kits done
A6: M1 · Foundation | B6: Group | C6: Tech backbone | D6: Shopify + domains + WhatsApp API + payments + analytics + n8n + inventory + accounting live | E6: Arihant | F6: All core systems live & connected
A7: M1 · Foundation | B7: Aurra Hype | C7: Store + Launch | D7: Upgrade store, shoot catalog, POS live, amplify 12 Jul store launch as content+PR | E7: Arihant + Designomics | F7: Store launch = 500+ footfall / big content spike
A8: M1 · Foundation | B8: Group | C8: Content engine | D8: Photo/video pod running; 3-5 reels/wk per brand; social calendars live | E8: Arihant content pod | F8: 90+ assets shipped · consistent posting
A9: M1 · Foundation | B9: Group | C9: Packaging | D9: Branded boxes/mailers + inserts designed & ordered; gift-box configurator live | E9: Designomics | F9: Branded unboxing shipping on every order
A10: M1 · Foundation | B10: Aurra Hype | C10: Paid ads on | D10: Meta always-on live; pixel/CAPI; first creative tests | E10: Arihant | F10: First profitable campaigns · ROAS baseline set
A11: M2 · Engine (Wk 5-8) | B11: Aurra Hype | C11: Scale paid + CRO | D11: Add Google/PMax; scale winners; CRO; email/SMS/WhatsApp flows live | E11: Arihant | F11: ROAS ≥ 2.5 · repeat-rate flows recovering revenue
A12: M2 · Engine | B12: Group | C12: Automations | D12: Deploy cart recovery, order updates, chatbot, ops digest, review flow | E12: Arihant | F12: 10+ automations live · support tickets down
A13: M2 · Engine | B13: Aurra Hype | C13: Marketplaces | D13: Launch Amazon + Flipkart with A+ content + ads | E13: Arihant | F13: Live on 2 marketplaces · first marketplace sales
A14: M2 · Engine | B14: Designomics | C14: Corporate gifting | D14: Outbound to corporates; catalog + quote system; festive push | E14: Founder + Arihant | F14: 5+ corporate gifting deals in pipeline
A15: M2 · Engine | B15: Loop In | C15: Pipeline | D15: New brand launch; lead-gen ads; CRM; 2-3 signature events booked | E15: Loop In + Arihant | F15: 3 events booked · case studies started
... A21: M3 · Scale | B21: Group | C21: Prove the numbers | D21: Full unit-economics review; investor/partner deck from real data | E21: Arihant + CA | F21: Documented growth curve · CAC/AOV/ROAS/repeat proof

Sheet Q-Commerce & Marketplaces
A1: Q-COMMERCE & MARKETPLACE CHANNELS
A2: Real 2026 India onboarding costs & fit. Verify current terms at signup — platforms change fast.
A4: Channel | B4: Best for | C4: Onboarding cost / model | D4: Commission | E4: Fit for group | F4: Priority | G4: Notes
A5: Amazon India | B5: Aurra Hype apparel, Designomics gifting | C5: Free account; pay-per-sale + optional FBA | D5: ~10-20% + fees | E5: High — discovery + trust | F5: P1 | G5: A+ content + Sponsored Products; use FBA for Prime badge
A6: Flipkart | B6: Apparel + gifting, tier 2/3 reach | C6: Free listing; commission per sale | D6: ~5-20% | E6: High | F6: P1 | G6: Flipkart Ads + Big Billion Days spikes
A7: Myntra | B7: Aurra Hype fashion-native buyers | C7: Brand approval needed | D7: ~25-40% effective | E7: Medium-High | F7: P2 | G7: Category-native; higher take rate; strong for streetwear
A8: Ajio | B8: Aurra Hype fashion | C8: Brand onboarding | D8: ~high | E8: Medium | F8: P2 | G8: Reliance ecosystem; good festive events
A9: Blinkit | B9: Designomics impulse gifting SKUs | C9: ~₹25k/SKU/state listing (as ad credits) + ~₹2-3L/mo marketing | D9: 15-25% + fees | E9: Medium (needs >65% margin) | F9: P3 | G9: Selective onboarding; best for fast-moving low-price gifts
A10: Zepto | B10: Premium gifting positioning | C10: Bundled packages ~₹5-6L to start; Atom analytics ₹30k/mo | D10: 10-25% | E10: Low-Medium | F10: P3 | G10: Expensive entry; only after product-market fit
A11: Swiggy Instamart | B11: Easiest q-comm entry, South India | C11: No onboarding fee; weekly POs ~₹2-5k | D11: 15-25% | E11: Medium | F11: P3 | G11: Lightest commitment to test q-commerce
A12: Meesho | B12: Value gifting / stickers volume | C12: Free; 0% commission model | D12: Low | E12: Medium | F12: P2 | G12: Great for low-price, high-volume Designomics SKUs
A13: Own D2C (Shopify) | B13: All — highest margin | C13: Owned stack | D13: 0% (only gateway ~2%) | E13: Core | F13: P0 | G13: Always the priority channel; marketplaces feed it
A14: WhatsApp Commerce | B14: Repeat + gifting + drops | C14: API ~₹5-10k/mo | D14: Per-conversation | E14: High | F14: P1 | G14: Catalog + broadcast + checkout; India's highest-converting channel

Sheet Budget Summary
A1: BUDGET SUMMARY — by Domain
A2: Rolled up live from Master Stack (SUMIF). Ad spend included in monthly. Aggressive-spend scenario.
A4: Domain | B4: Setup (₹, one-time) | C4: Monthly (₹) | D4: 3-Month Run (₹)
A5: Brand & Identity | B5: =SUMIF('Master Stack'!C:C,A5,'Master Stack'!J:J) -> 195000 | C5: =SUMIF('Master Stack'!C:C,A5,'Master Stack'!K:K) -> 0 | D5: =B5+C5*3 -> 195000
A6: Website & E-commerce | B6: =SUMIF('Master Stack'!C:C,A6,'Master Stack'!J:J) -> 100000 | C6: =SUMIF('Master Stack'!C:C,A6,'Master Stack'!K:K) -> 15500 | D6: =B6+C6*3 -> 146500
A7: Content & Creative | B7: =SUMIF('Master Stack'!C:C,A7,'Master Stack'!J:J) -> 120000 | C7: =SUMIF('Master Stack'!C:C,A7,'Master Stack'!K:K) -> 106000 | D7: =B7+C7*3 -> 438000
A8: Performance Marketing | B8: =SUMIF('Master Stack'!C:C,A8,'Master Stack'!J:J) -> 0 | C8: =SUMIF('Master Stack'!C:C,A8,'Master Stack'!K:K) -> 358000 | D8: =B8+C8*3 -> 1074000
A9: Organic & Social | B9: =SUMIF('Master Stack'!C:C,A9,'Master Stack'!J:J) -> 0 | C9: =SUMIF('Master Stack'!C:C,A9,'Master Stack'!K:K) -> 110000 | D9: =B9+C9*3 -> 330000
A10: SEO / GEO / AEO | B10: =SUMIF('Master Stack'!C:C,A10,'Master Stack'!J:J) -> 35000 | C10: =SUMIF('Master Stack'!C:C,A10,'Master Stack'!K:K) -> 22000 | D10: =B10+C10*3 -> 101000
A11: CRM & Retention | B11: =SUMIF('Master Stack'!C:C,A11,'Master Stack'!J:J) -> 5000 | C11: =SUMIF('Master Stack'!C:C,A11,'Master Stack'!K:K) -> 20500 | D11: =B11+C11*3 -> 66500
A12: AI & Automation | B12: =SUMIF('Master Stack'!C:C,A12,'Master Stack'!J:J) -> 6000 | C12: =SUMIF('Master Stack'!C:C,A12,'Master Stack'!K:K) -> 19000 | D12: =B12+C12*3 -> 63000
A13: Customer Support | B13: =SUMIF('Master Stack'!C:C,A13,'Master Stack'!J:J) -> 0 | C13: =SUMIF('Master Stack'!C:C,A13,'Master Stack'!K:K) -> 9000 | D13: =B13+C13*3 -> 27000
A14: Sourcing & Manufacturing | B14: =SUMIF('Master Stack'!C:C,A14,'Master Stack'!J:J) -> 10000 | C14: =SUMIF('Master Stack'!C:C,A14,'Master Stack'!K:K) -> 0 | D14: =B14+C14*3 -> 10000
A15: Packaging & Unboxing | B15: =SUMIF('Master Stack'!C:C,A15,'Master Stack'!J:J) -> 55000 | C15: =SUMIF('Master Stack'!C:C,A15,'Master Stack'!K:K) -> 33000 | D15: =B15+C15*3 -> 154000
A16: Inventory & Warehouse | B16: =SUMIF('Master Stack'!C:C,A16,'Master Stack'!J:J) -> 58000 | C16: =SUMIF('Master Stack'!C:C,A16,'Master Stack'!K:K) -> 14500 | D16: =B16+C16*3 -> 101500
... A24: Analytics & BI | B24: =SUMIF('Master Stack'!C:C,A24,'Master Stack'!J:J) -> 5000 | C24: =SUMIF('Master Stack'!C:C,A24,'Master Stack'!K:K) -> 11000 | D24: =B24+C24*3 -> 38000
A25: TOTAL | B25: =SUM(B5:B24) -> 835000 | C25: =SUM(C5:C24) -> 1120000 | D25: =SUM(D5:D24) -> 4195000
A27: Note: 'In-house' work by Arihant/Designomics is shown at internal tool cost, not agency price — that spread is the group's structural margin advantage. Ad budgets scale with ROAS; treat monthly ad lines as starting floors, not caps.
