Workbook

Sheet Overview
A1: HARSHDEEP GROUP — MASTER OPERATING STACK (FULL / ADVANCED)
A2: 4 brands · world-class + advanced global tooling · AI-native · Founder OS · Prepared Jul 2026
A4: THE 4 ASSETS
A5: Aurra Hype | B5: D2C streetwear / hype apparel (Bengaluru). Store + office launch 12 Jul. aurahyped.com.
A6: Designomics India | B6: Personalised gifting + merch + apparel (custom boxes, stickers, mugs, tees, workshops, corporate gifting). Also the group's in-house design/print/packaging arm.
A7: Loop In Events | B7: Event management & experiential. NAME/DOMAIN CLASH with a Canadian firm (loopinevents.com) — rebrand + trademark first. Also the group's live-activation arm.
A8: Arihant Digital | B8: ~10-yr digital agency = the in-house engine (web, performance, SEO/GEO, automation, analytics). Builds the 3 brands at cost, then sells the proven capability to outside clients.
A10: WHAT'S NEW IN THIS FULL VERSION
A11: Advanced global stack | B11: Best-in-class tools world-class brands actually use (Shopify, Klaviyo, Triple Whale, Motion, Attentive, Gorgias, GRIN, etc.) added across every function.
A12: AI & creative engine | B12: Full 2026 AI stack: Higgsfield (UGC ad video), Veo 3.1 / Runway / Kling (video), Midjourney / Krea / Ideogram (image), ElevenLabs / HeyGen (voice+avatar), Claude + MCP, Gemini.
A13: Chat & social automation | B13: IG comment-to-DM, WhatsApp API, Telegram, Facebook/Messenger via ManyChat + AiSensy + n8n agents.
A14: Founder OS | B14: A single command center to run all 4 brands: dashboards, daily/weekly/monthly cadence, founder-level automations & AI copilots. See 'Founder OS' tab + separate playbook doc.
A15: Per-brand tabs | B15: Dedicated deep tab for each of the 4 brands with its own priority stack.
A16: World-class benchmarks | B16: 'Benchmarks' tab: what leading global brands use, by function, so you copy proven playbooks.
A18: HOW TO READ
A19: Priority | B19: P0 = Month 1 (foundation) · P1 = Month 2 (engine) · P2 = Month 3 (scale) · P3 = later / advanced.
A20: In-house vs Buy | B20: In-house: Arihant (digital/marketing) · In-house: Designomics (design/print/merch) · Buy (SaaS/vendor) · Hybrid.
A21: Costs | B21: INR unless a tool is billed in USD (AI tools tab shows USD). Aggressive-spend scenario. Ad budgets are separate line items.

Sheet Master Stack
A1: MASTER STACK — every service · software · automation (advanced, all 4 brands)
A2: P0→P3 priority · in-house vs buy · vendor · cost · phase. Filterable.
A4: # | B4: Business | C4: Domain | D4: Item / Capability | E4: What it does & why it matters | F4: Type | G4: Priority | H4: In-house vs Buy | I4: Recommended Tool / Vendor | J4: Setup (₹) | K4: Monthly (₹) | L4: Phase
A5: 1 | B5: Group | C5: Brand & Identity | D5: Group holding-brand & naming architecture | E5: How the 4 sub-brands relate; fixes inconsistent identity | F5: Service | G5: P0 | H5: In-house: Designomics | I5: Designomics | J5: 40000 | K5: 0 | L5: M1
A6: 2 | B6: Loop In | C6: Brand & Identity | D6: Rebrand (name+logo+identity) | E6: Resolve Canada clash; trademarkable name | F6: Service | G6: P0 | H6: In-house: Designomics | I6: Designomics + IP attorney | J6: 60000 | K6: 0 | L6: M1
A7: 3 | B7: Aurra Hype | C7: Brand & Identity | D7: Identity refinement + trademark | E7: Stand out from crowded 'Aura/Aurra' space | F7: Service | G7: P0 | H7: In-house: Designomics | I7: Designomics | J7: 30000 | K7: 0 | L7: M1
A8: 4 | B8: Group | C8: Brand & Identity | D8: Trademark search + filing (key classes) | E8: Legal ownership; blocks copycats | F8: Service | G8: P0 | H8: Buy | I8: IP attorney / IPIndia | J8: 45000 | K8: 0 | L8: M1
A9: 5 | B9: Group | C9: Brand & Identity | D9: Brand voice + messaging system | E9: Consistent tone across all channels & AI prompts | F9: Service | G9: P1 | H9: In-house: Arihant | I9: Brand book + GPT/Claude style guide | J9: 15000 | K9: 0 | L9: M2
A10: 6 | B10: Aurra Hype | C10: Website & E-commerce | D10: Shopify store (headless-ready) | E10: Fast conversion storefront + app ecosystem | F10: SaaS | G10: P0 | H10: In-house: Arihant | I10: Shopify → Plus later | J10: 25000 | K10: 3500 | L10: M1
A11: 7 | B11: Designomics | C11: Website & E-commerce | D11: Replatform off Wix + custom-box builder | E11: Configurator UX, apps, speed | F11: SaaS | G11: P1 | H11: In-house: Arihant | I11: Shopify + Kickflip/Zakeke | J11: 30000 | K11: 5000 | L11: M2
A12: 8 | B12: Loop In | C12: Website & E-commerce | D12: Lead-gen site + portfolio + booking | E12: Enquiries, case studies, packages | F12: Service | G12: P0 | H12: In-house: Arihant | I12: Webflow / WordPress | J12: 25000 | K12: 1500 | L12: M1
A13: 9 | B13: Group | C13: Website & E-commerce | D13: Landing-page / funnel builder | E13: Fast campaign & drop landing pages | F13: SaaS | G13: P1 | H13: In-house: Arihant | I13: Replo / Unbounce | J13: 0 | K13: 4000 | L13: M2
A14: 10 | B14: Aurra Hype | C14: Website & E-commerce | D14: On-site personalization + upsell | E14: Higher AOV via smart recommendations | F14: SaaS | G14: P2 | H14: Buy | I14: Rebuy / Nosto | J14: 0 | K14: 8000 | L14: M3
A15: 11 | B15: Group | C15: Website & E-commerce | D15: A/B testing & CRO | E15: Systematic conversion lift on paid traffic | F15: SaaS | G15: P2 | H15: In-house: Arihant | I15: VWO / Intelligems | J15: 0 | K15: 9000 | L15: M3
A16: 12 | B16: Group | C16: Website & E-commerce | D16: Domains, SSL, email, DNS, CDN | E16: Professional infra across brands | F16: Infra | G16: P0 | H16: In-house: Arihant | I16: Google Workspace + Cloudflare | J16: 5000 | K16: 3000 | L16: M1
... A106: 102 | B106: Aurra Hype | C106: Analytics & BI | D106: Session replay + heatmaps | E106: See where users drop; fix UX | F106: SaaS | G106: P2 | H106: In-house: Arihant | I106: Microsoft Clarity (free) / Hotjar | J106: 0 | K106: 0 | L106: M3
I107: TOTALS → | J107: =SUM(J5:J106) -> 795000 | K107: =SUM(K5:K106) -> 1259500

Sheet Aurra Hype
A1: Aurra Hype — Brand Playbook
A2: D2C streetwear / hype apparel · Bengaluru · store+office launch 12 Jul
A4: POSITIONING: The drop-driven Indian streetwear label. Win = desirable product + hype/scarcity rhythm + disciplined performance marketing with healthy unit economics. Copy the global streetwear playbook (limited drops, community, resale hype).
A6: Priority | B6: Workstream | C6: Key action / what to build | D6: Tool / Owner | E6: Proof / outcome
A7: P0 | B7: Brand & Trademark | C7: Refine identity vs crowded 'Aura' space; file trademark | D7: Designomics + IP attorney | E7: Distinct, owned brand
A8: P0 | B8: Store | C8: Shopify build, reviews, upsell, 1-tap UPI/COD checkout | D8: Arihant + GoKwik | E8: CVR > 2%, fast store
A9: P0 | B9: Retail | C9: POS unifying store+online stock; amplify 12 Jul launch as content/PR | D9: Arihant + Loop In | E9: 500+ footfall, viral launch
A10: P0 | B10: Creative | C10: Catalog + lifestyle shoot; reels engine 3-5/wk | D10: Content pod | E10: 90+ assets in M1
A11: P0 | B11: Paid | C11: Meta always-on; pixel+CAPI; creative testing | D11: Arihant + Motion | E11: ROAS baseline set
A12: P1 | B12: Paid scale | C12: Add Google Shopping/PMax; scale winners; profit analytics | D12: Arihant + Triple Whale | E12: ROAS >= 2.5
A13: P1 | B13: AI creative | C13: Higgsfield UGC ads + Runway/Veo hero drop films | D13: Arihant | E13: Cheaper, faster ad volume
A14: P1 | B14: Retention | C14: Klaviyo email/SMS + WhatsApp flows; loyalty | D14: Arihant + AiSensy | E14: Repeat-rate rising
A15: P1 | B15: Drops | C15: Drop calendar w/ scarcity, waitlists, early-access | D15: Arihant | E15: Sell-through per drop
A16: P1 | B16: Influencer | C16: Micro+mid seeding; UGC pipeline | D16: GRIN/Aspire + local | E16: Reach + UGC library
A17: P1 | B17: Marketplace | C17: Amazon + Flipkart w/ A+ content | D17: Arihant | E17: Live on 2 marketplaces
... A20: P3 | B20: Community | C20: Drop community (WhatsApp/Telegram VIP + Discord) | D20: Arihant | E20: Owned hype channel

Sheet Designomics
A1: Designomics — Brand Playbook
A2: Personalised gifting + merch + apparel · corporate gifting · in-house design/print arm
A4: POSITIONING: Two demand engines: impulse/occasion D2C gifting AND contract corporate gifting. Highest natural margin of the group; premium comes from a great customization UX. Also produces the group's design, print and packaging.
A6: Priority | B6: Workstream | C6: Key action / what to build | D6: Tool / Owner | E6: Proof / outcome
A7: P0 | B7: Replatform | C7: Move off Wix; custom gift-box configurator; apps + speed | D7: Arihant + Kickflip | E7: Higher AOV, better UX
A8: P0 | B8: Supply | C8: Merch/gifting supplier network + POD fallback | D8: Buy + Qikink | E8: Reliable catalog
A9: P0 | B9: Packaging | C9: Own the group's packaging + unboxing system | D9: Designomics | E9: Branded unboxing on every order
A10: P1 | B10: Corporate B2B | C10: Outbound to companies; catalog; quote-to-order; GST bulk | D10: Founder + HubSpot | E10: 5+ corporate deals in pipeline
A11: P1 | B11: Paid | C11: Meta + Google on gifting & corporate intent; festive push | D11: Arihant | E11: Profitable seasonal spend
A12: P1 | B12: AI creative | C12: AI product visuals (Midjourney/Krea) for endless SKUs | D12: Designomics | E12: Catalog-ready visuals cheaply
A13: P1 | B13: Retention | C13: Occasion automation (birthday/festival/anniversary) | D13: Klaviyo + AiSensy | E13: Recurring gifting revenue
A14: P2 | B14: Marketplace | C14: Meesho (volume) + Amazon gifting + Etsy (export optional) | D14: Arihant | E14: New discovery channels
A15: P2 | B15: Workshops | C15: Productise workshops (DTF/patch kits) as events + content | D15: Loop In + Designomics | E15: Community + revenue
A16: P3 | B16: Q-commerce | C16: Pilot Blinkit/Zepto on high-margin fast SKUs only | D16: Buy | E16: Impulse gifting channel

Sheet Loop In (rebrand)
A1: Loop In (rebrand) — Brand Playbook
A2: Event management & experiential · REBRAND FIRST (Canada name/domain clash) · group's live-activation arm
A4: POSITIONING: Runs the group's launches, pop-ups, drops and corporate-gifting experiences, and sells events externally. MUST rebrand: 'Loop In Events' + loopinevents.com belong to a Canadian planner. Secure a distinct, trademarked name + domain before scaling.
A6: Priority | B6: Workstream | C6: Key action / what to build | D6: Tool / Owner | E6: Proof / outcome
A7: P0 | B7: REBRAND | C7: IP-India search (Class 41 & 35); pick distinct name; lock domain+handles; file TM | D7: Founder + IP attorney | E7: Owned, trademarkable brand
A8: P0 | B8: Web | C8: Lead-gen site + portfolio + packages + booking | D8: Arihant | E8: Enquiries flowing
A9: P1 | B9: Pipeline | C9: Local + LinkedIn lead-gen; sales CRM; quote system | D9: Arihant + HubSpot | E9: 3 events booked
A10: P1 | B10: Ops | C10: Event project + vendor management system | D10: Monday.com + Aisle Planner | E10: On-time, on-budget events
A11: P1 | B11: Cross-sell | C11: Run Aurra Hype launches + Designomics corporate experiences | D11: Group | E11: Internal revenue + case studies
A12: P2 | B12: Content | C12: Film every event as reels/case studies/testimonials | D12: Content pod | E12: Portfolio + social proof
A13: P2 | B13: Automation | C13: Post-event feedback + testimonial + upsell flow | D13: Arihant + n8n | E13: Reviews + repeat bookings
A14: P3 | B14: Scale | C14: Signature owned event/IP (e.g. streetwear x music night) | D14: Group | E14: Brand-building flagship

Sheet Arihant Digital
A1: Arihant Digital — Brand Playbook
A2: ~10-yr digital agency = the in-house engine AND a productised external offer
A4: POSITIONING: The unfair advantage. Builds & markets the 3 brands at internal cost, then sells that battle-tested, AI-native capability to outside clients. The 3 brands become its case studies. This is how the group funds itself and compounds.
A6: Priority | B6: Workstream | C6: Key action / what to build | D6: Tool / Owner | E6: Proof / outcome
A7: P0 | B7: Internal delivery | C7: Deliver web, ads, SEO/GEO, automation, analytics to all 3 brands | D7: Arihant team | E7: 3 brands live & scaling
A8: P1 | B8: Productise | C8: Package offers: 'AI-native growth', 'store build', 'automation setup' | D8: Founder | E8: Clear sellable packages
A9: P1 | B9: Proof assets | C9: Turn brand wins into case studies + before/after numbers | D9: Arihant | E9: Portfolio of real results
A10: P1 | B10: AI edge | C10: Lead with AI creative (Higgsfield) + automation (n8n/MCP) as differentiator | D10: Arihant | E10: Premium positioning
A11: P2 | B11: Outbound | C11: Cold + inbound + referrals; sell to D2C brands like your own | D11: Founder + HubSpot | E11: First external clients
A12: P2 | B12: Retainers | C12: Move clients to monthly retainers (predictable revenue) | D12: Arihant | E12: MRR base
A13: P3 | B13: Scale team | C13: Hire pod-based delivery; SOPs; margins | D13: Founder | E13: Scalable agency

Sheet AI & Creative Stack
A1: AI & CREATIVE STACK (2026, world-class)
A2: The AI engine world-class brands use. USD pricing indicative — verify at signup; models move fast.
A4: Category | B4: Tool | C4: What it does | D4: Best for | E4: Approx price (USD/mo) | F4: Priority
A5: Video — UGC ads | B5: Higgsfield (Hermes Agent) | C5: Product URL → ready UGC/CGI ad video; aggregates 15+ models | D5: Meta/TikTok ad volume, testimonials, unboxings | E5: $15–84 | F5: P1
A6: Video — cinematic | B6: Google Flow (Veo 3.1) | C6: Best overall AI video + native audio, 4K | D6: Hero brand films, drop teasers | E6: ~$20+ | F6: P1
A7: Video — control | B7: Runway (Gen-4.5) | C7: Keyframes, motion brush, character consistency, editor | D7: Marketer-controlled brand video | E7: $15–95 | F7: P1
A8: Video — value | B8: Kling 3.0 | C8: Cheapest premium model (~$0.10/s), multi-shot | D8: High-volume iteration | E8: pay-as-you-go | F8: P2
A9: Video — repurpose | B9: Opus Clip / Descript | C9: 1 long video → many captioned clips; edit by text | D9: Reels/Shorts factory, podcasts | E9: $15–30 | F9: P1
A10: Image — concept | B10: Midjourney | C10: Best-in-class stylised imagery | D10: Moodboards, campaign concepts | E10: $10–60 | F10: P0
A11: Image — realtime | B11: Krea / Leonardo | C11: Real-time + model hub (Flux etc.) | D11: Fast product/lifestyle variations | E11: $10–60 | F11: P1
A12: Image — text/logo | B12: Ideogram | C12: Best text-in-image + logo/poster | D12: Posters, packaging art, typography | E12: $8–48 | F12: P2
A13: Image — product | B13: Photoroom / Flair | C13: Background removal + AI product scenes | D13: Catalog + on-model shots | E13: $10–40 | F13: P0
A14: Voice | B14: ElevenLabs | C14: Realistic AI voiceover, many languages | D14: Ad VO, IVR, dubbing | E14: $5–99 | F14: P2
A15: Avatar | B15: HeyGen | C15: Talking-avatar spokesperson videos | D15: Multilingual promos, explainers | E15: $29–89 | F15: P2
... A23: Profit analytics | B23: Triple Whale | C23: True profit/attribution per creative/channel | D23: D2C financial truth | E23: $129–499 | F23: P1

Sheet Automation Catalogue
A1: AUTOMATION CATALOGUE
A2: Build on n8n/Make + WhatsApp API + ManyChat + GPT/Claude(MCP). Channel-tagged.
A4: # | B4: Automation | C4: Channel | D4: Business | E4: Trigger → Action | F4: Tools | G4: Impact
A5: 1 | B5: Abandoned-cart recovery | C5: WhatsApp+Email | D5: Aurra/Design | E5: Cart not completed → timed WA+email w/ product+offer | F5: Shopify+Klaviyo+AiSensy+n8n | G5: Recovers 8-15% carts
A6: 2 | B6: Order status updates | C6: WhatsApp | D6: All | E6: Placed/shipped/OFD/delivered → auto WA w/ tracking | F6: Shiprocket+WA API+n8n | G6: -60% WISMO tickets
A7: 3 | B7: IG comment-to-DM funnel | C7: Instagram | D7: Aurra/Design | E7: Comment keyword → auto DM link/coupon → capture | F7: ManyChat | G7: Turns engagement into sales
A8: 4 | B8: IG/DM auto-reply + qualify | C8: Instagram | D8: All | E8: DM in → AI reply, sizing/FAQ, qualify, handoff | F8: ManyChat + Chatbase | G8: 24x7 IG selling
A9: 5 | B9: WhatsApp catalog + checkout | C9: WhatsApp | D9: Aurra/Design | E9: Browse catalog, order, pay on WhatsApp | F9: AiSensy + Razorpay | G9: High-converting channel
A10: 6 | B10: Telegram drops/VIP broadcast | C10: Telegram | D10: Aurra | E10: New drop → broadcast to VIP list + early access | F10: Telegram Bot + n8n | G10: Owned hype channel
A11: 7 | B11: Facebook lead → CRM | C11: Facebook | D11: Loop In/Design | E11: Lead ad → CRM → auto WA/email + assign | F11: ManyChat + HubSpot + n8n | G11: No lead dropped
A12: 8 | B12: AI support chatbot | C12: Site+WA | D12: All | E12: Any query → sizing/returns/status; human handoff | F12: Gorgias AI / Chatbase | G12: 24x7 support
A13: 9 | B13: Review + UGC request | C13: WhatsApp+Email | D13: Aurra/Design | E13: Delivered +5d → ask review+photo, reward coupon | F13: Judge.me/Loox+WA+n8n | G13: Social proof + UGC
A14: 10 | B14: AI ad-creative pipeline | C14: Internal | D14: All | E14: New SKU → Higgsfield UGC ad + captions auto-drafted | F14: Higgsfield+GPT+n8n | G14: Ad volume, -70% time
A15: 11 | B15: AI product imagery | C15: Internal | D15: Aurra/Design | E15: New SKU → on-model + scene images auto-generated | F15: Photoroom/Krea+n8n | G15: Catalog-ready fast
A16: 12 | B16: Daily founder digest | C16: WhatsApp/Telegram | D16: Group | E16: 8am → sales, spend, ROAS, top SKUs, low stock | F16: Sheets+GA4+Meta+GPT+n8n | G16: One-glance control
... A26: 22 | B26: Meeting → action items | C26: Internal | D26: Group | E26: Call ends → AI notes + tasks to project tool | F26: Fathom/Fireflies+Notion | G26: Nothing falls through

Sheet Founder OS
A1: FOUNDER OPERATING SYSTEM
A2: One command center to run all 4 brands. Full detail in the Founder OS playbook doc.
A4: Layer | B4: What it is | C4: Tools | D4: Cadence / notes
A5: 1 · Command Center | B5: Single dashboard: revenue, CAC, ROAS, AOV, cash, stock, pipeline — all 4 brands | C5: Looker Studio + Triple Whale + Sheets (fed by n8n) | D5: Live; check each morning
A6: 2 · Daily digest | B6: 8am WhatsApp/Telegram summary + anomalies + to-dos | C6: n8n + GPT + WhatsApp/Telegram | D6: Daily, automated
A7: 3 · AI Chief of Staff | B7: Ask questions across your data via Claude + MCP connectors (Shopify, ads, CRM, Sheets) | C7: Claude + MCP servers | D7: On-demand, conversational
A8: 4 · Work system | B8: All brand workstreams, tasks, SOPs in one place | C8: Notion / ClickUp | D8: Weekly review
A9: 5 · Time & focus | B9: AI auto-schedules deep work, meetings, priorities | C9: Motion (usemotion) / Reclaim | D9: Daily auto-planning
A10: 6 · Meetings | B10: Auto notes + action items pushed to tasks | C10: Fathom / Fireflies | D10: Every call
A11: 7 · Comms hub | B11: One inbox: email, IG, WhatsApp, chat | C11: Gorgias / shared inbox + Superhuman | D11: Batch 2x/day
A12: 8 · Money view | B12: Spend, burn, runway, approvals across brands | C12: Volopay/Jify + Zoho Books | D12: Weekly
A13: 9 · Approvals | B13: Creative, spend, hires flow to you for 1-tap approve | C13: n8n + WhatsApp/Slack | D13: Async
A14: 10 · Weekly scorecard | B14: Auto scorecard vs targets per brand + team accountability | C14: Looker + n8n | D14: Monday review

Sheet Benchmarks
A1: WORLD-CLASS BENCHMARKS — what leading brands use, by function
A2: Copy proven playbooks. Match your function to the best-in-class default.
A4: Function | B4: World-class default stack | C4: Example brands (global/India) | D4: Your move
A5: D2C platform | B5: Shopify (→ Plus at scale) | C5: Gymshark, Allbirds, boAt, Sugar | D5: Shopify for Aurra + Designomics
A6: Email/SMS retention | B6: Klaviyo (+ Attentive/Postscript SMS) | C6: Vuori, Ridge, Mamaearth | D6: Klaviyo + WhatsApp (India)
A7: Profit analytics | B7: Triple Whale (50k+ brands) | C7: Ridge, Obvi | D7: Triple Whale for Aurra
A8: Creative analytics | B8: Motion | C8: Vuori, Keeps, Ridge | D8: Motion once ad spend scales
A9: AI ad creative | B9: Higgsfield + Runway + Veo | C9: AI-native D2C brands 2026 | D9: Higgsfield for UGC ad volume
A10: Chat automation | B10: ManyChat (IG/WA) | C10: Creators + D2C at scale | D10: ManyChat + AiSensy
A11: Support | B11: Gorgias (AI-first) | C11: Steve Madden, Princess Polly | D11: Gorgias AI across brands
A12: Influencer | B12: GRIN / Aspire / Upfluence | C12: SKIMS, Glossier | D12: GRIN once seeding scales
A13: Reviews/UGC | B13: Okendo / Loox / Judge.me | C13: Premium D2C | D13: Judge.me/Loox on Shopify
A14: Subscriptions | B14: Recharge / Loop | C14: Athletic Greens | D14: Only if gifting subscription boxes
A15: Returns | B15: Loop Returns / Return Prime | C15: Fashion D2C | D15: Return Prime (India)
... A20: Time management | B20: Motion (usemotion) | C20: Founders/execs | D20: Motion for founder focus

Sheet 90-Day Roadmap
A1: 90-DAY SCALE ROADMAP
A2: M1 Foundation · M2 Engine · M3 Scale. 'Proof' = milestone that shows it's working.
A4: Phase | B4: Business | C4: Workstream | D4: Key actions | E4: Owner | F4: Proof / KPI
A5: M1 · Foundation | B5: Group | C5: Legal + Brand | D5: Clean entities/GST; TM search+file x3; rebrand Loop In; unify brands | E5: Founder+CA+Designomics | F5: 3 TMs filed · Loop In relaunched
A6: M1 · Foundation | B6: Group | C6: Tech backbone | D6: Shopify+domains+WA API+payments+analytics+n8n+inventory+accounting live | E6: Arihant | F6: All core systems connected
A7: M1 · Foundation | B7: Aurra Hype | C7: Store + launch | D7: Store upgrade, catalog shoot, POS, amplify 12 Jul launch | E7: Arihant+Designomics+Loop In | F7: 500+ footfall · content spike
A8: M1 · Foundation | B8: Group | C8: Content + AI | D8: Content pod live; AI creative stack (Higgsfield/Midjourney) set up | E8: Arihant | F8: 90+ assets · AI pipeline live
A9: M1 · Foundation | B9: Group | C9: Packaging | D9: Branded boxes/inserts ordered; gift-box configurator live | E9: Designomics | F9: Branded unboxing shipping
A10: M1 · Foundation | B10: Aurra Hype | C10: Paid on | D10: Meta always-on; pixel/CAPI; first tests | E10: Arihant | F10: ROAS baseline set
A11: M2 · Engine | B11: Aurra Hype | C11: Scale paid + CRO | D11: Add Google/PMax; scale winners; Klaviyo+WA flows | E11: Arihant+Triple Whale | F11: ROAS >= 2.5 · repeat flows live
A12: M2 · Engine | B12: Group | C12: Automations | D12: Cart recovery, order updates, IG/WA bots, digest, reviews | E12: Arihant | F12: 15+ automations live
A13: M2 · Engine | B13: Aurra Hype | C13: Marketplaces | D13: Amazon + Flipkart w/ A+ content + ads | E13: Arihant | F13: Live on 2 marketplaces
A14: M2 · Engine | B14: Designomics | C14: Corporate gifting | D14: Outbound + catalog + quote system; festive push | E14: Founder+Arihant | F14: 5+ corporate deals in pipeline
A15: M2 · Engine | B15: Loop In | C15: Pipeline | D15: Relaunch; lead-gen; CRM; 2-3 events booked | E15: Loop In+Arihant | F15: 3 events booked · case studies
... A21: M3 · Scale | B21: Group | C21: Prove numbers | D21: Full unit-economics; investor/partner deck from real data | E21: Arihant+CA | F21: Documented growth curve

Sheet Q-Commerce & Marketplaces
A1: Q-COMMERCE & MARKETPLACE CHANNELS
A2: Real 2026 India costs & fit. Verify terms at signup.
A4: Channel | B4: Best for | C4: Onboarding cost / model | D4: Commission | E4: Fit | F4: Priority | G4: Notes
A5: Own D2C (Shopify) | B5: All — highest margin | C5: Owned stack | D5: ~2% gateway only | E5: Core | F5: P0 | G5: Always the priority channel
A6: WhatsApp Commerce | B6: Repeat + gifting + drops | C6: API ~₹5-10k/mo | D6: per-conversation | E6: High | F6: P0 | G6: India's highest-converting channel
A7: Amazon India | B7: Apparel + gifting | C7: Free acct; pay-per-sale; optional FBA | D7: ~10-20%+ | E7: High | F7: P1 | G7: A+ content + Sponsored Products
A8: Flipkart | B8: Apparel + gifting | C8: Free listing; per-sale | D8: ~5-20% | E8: High | F8: P1 | G8: Big Billion Days spikes
A9: Meesho | B9: Value gifting/stickers volume | C9: Free; 0% commission | D9: Low | E9: Medium | F9: P2 | G9: Great for low-price high-volume
A10: Myntra | B10: Aurra fashion-native | C10: Brand approval | D10: ~25-40% eff. | E10: Med-High | F10: P2 | G10: Strong for streetwear
A11: Ajio | B11: Aurra fashion | C11: Brand onboarding | D11: high | E11: Medium | F11: P2 | G11: Reliance ecosystem
A12: Etsy (export) | B12: Designomics stickers/gifting | C12: Free; listing+txn fees | D12: ~6.5%+ | E12: Med (global) | F12: P3 | G12: Optional international reach
A13: Blinkit | B13: Impulse gifting SKUs | C13: ~₹25k/SKU/state (ad credits)+₹2-3L/mo | D13: 15-25%+ | E13: Med (need >65% margin) | F13: P3 | G13: Selective; fast movers only
A14: Zepto | B14: Premium gifting | C14: Bundled ~₹5-6L; Atom ₹30k/mo | D14: 10-25% | E14: Low-Med | F14: P3 | G14: Expensive entry
A15: Swiggy Instamart | B15: Easiest q-comm test | C15: No fee; weekly POs ₹2-5k | D15: 15-25% | E15: Medium | F15: P3 | G15: Lightest q-comm commitment

Sheet Budget Summary
A1: BUDGET SUMMARY — by Domain
A2: Live SUMIF from Master Stack. Ad spend included in monthly. Aggressive scenario.
A4: Domain | B4: Setup (₹) | C4: Monthly (₹) | D4: 3-Month Run (₹)
A5: Brand & Identity | B5: =SUMIF('Master Stack'!C:C,A5,'Master Stack'!J:J) -> 190000 | C5: =SUMIF('Master Stack'!C:C,A5,'Master Stack'!K:K) -> 0 | D5: =B5+C5*3 -> 190000
A6: Website & E-commerce | B6: =SUMIF('Master Stack'!C:C,A6,'Master Stack'!J:J) -> 85000 | C6: =SUMIF('Master Stack'!C:C,A6,'Master Stack'!K:K) -> 34000 | D6: =B6+C6*3 -> 187000
A7: Content & Creative | B7: =SUMIF('Master Stack'!C:C,A7,'Master Stack'!J:J) -> 120000 | C7: =SUMIF('Master Stack'!C:C,A7,'Master Stack'!K:K) -> 70000 | D7: =B7+C7*3 -> 330000
A8: AI & Creative | B8: =SUMIF('Master Stack'!C:C,A8,'Master Stack'!J:J) -> 0 | C8: =SUMIF('Master Stack'!C:C,A8,'Master Stack'!K:K) -> 33000 | D8: =B8+C8*3 -> 99000
A9: Performance Marketing | B9: =SUMIF('Master Stack'!C:C,A9,'Master Stack'!J:J) -> 0 | C9: =SUMIF('Master Stack'!C:C,A9,'Master Stack'!K:K) -> 407000 | D9: =B9+C9*3 -> 1221000
A10: CRM & Retention | B10: =SUMIF('Master Stack'!C:C,A10,'Master Stack'!J:J) -> 5000 | C10: =SUMIF('Master Stack'!C:C,A10,'Master Stack'!K:K) -> 36000 | D10: =B10+C10*3 -> 113000
A11: Chat & Social Automation | B11: =SUMIF('Master Stack'!C:C,A11,'Master Stack'!J:J) -> 0 | C11: =SUMIF('Master Stack'!C:C,A11,'Master Stack'!K:K) -> 16500 | D11: =B11+C11*3 -> 49500
A12: AI & Automation | B12: =SUMIF('Master Stack'!C:C,A12,'Master Stack'!J:J) -> 6000 | C12: =SUMIF('Master Stack'!C:C,A12,'Master Stack'!K:K) -> 14000 | D12: =B12+C12*3 -> 48000
A13: Sourcing & Manufacturing | B13: =SUMIF('Master Stack'!C:C,A13,'Master Stack'!J:J) -> 10000 | C13: =SUMIF('Master Stack'!C:C,A13,'Master Stack'!K:K) -> 0 | D13: =B13+C13*3 -> 10000
A14: Packaging & Unboxing | B14: =SUMIF('Master Stack'!C:C,A14,'Master Stack'!J:J) -> 70000 | C14: =SUMIF('Master Stack'!C:C,A14,'Master Stack'!K:K) -> 43000 | D14: =B14+C14*3 -> 199000
A15: Inventory & Warehouse | B15: =SUMIF('Master Stack'!C:C,A15,'Master Stack'!J:J) -> 58000 | C15: =SUMIF('Master Stack'!C:C,A15,'Master Stack'!K:K) -> 16500 | D15: =B15+C15*3 -> 107500
A16: Order & Logistics | B16: =SUMIF('Master Stack'!C:C,A16,'Master Stack'!J:J) -> 0 | C16: =SUMIF('Master Stack'!C:C,A16,'Master Stack'!K:K) -> 27000 | D16: =B16+C16*3 -> 81000
... A24: Analytics & BI | B24: =SUMIF('Master Stack'!C:C,A24,'Master Stack'!J:J) -> 5000 | C24: =SUMIF('Master Stack'!C:C,A24,'Master Stack'!K:K) -> 4000 | D24: =B24+C24*3 -> 17000
A25: TOTAL | B25: =SUM(B5:B24) -> 795000 | C25: =SUM(C5:C24) -> 1259500 | D25: =SUM(D5:D24) -> 4573500
A27: In-house work by Arihant/Designomics is shown at internal tool cost, not agency price — that spread is the group's margin advantage. Ad + AI-tool lines are floors; scale with ROAS. AI tools billed in USD are approximated here in INR via their Master Stack lines.
